dbttoolkit/__init__.py
dbttoolkit/cli/__init__.py
dbttoolkit/cli/main.py
dbttoolkit/core/__init__.py
dbttoolkit/core/config.py
dbttoolkit/core/exceptions.py
dbttoolkit/core/io.py
dbttoolkit/core/sql.py
dbttoolkit/dialect/__init__.py
dbttoolkit/dialect/bigquery.py
dbt_tool_kit-1.0.1.dist-info/METADATA
dbt_tool_kit-1.0.1.dist-info/WHEEL
dbt_tool_kit-1.0.1.dist-info/entry_points.txt
dbt_tool_kit-1.0.1.dist-info/RECORD
