Metadata-Version: 2.1
Name: dbt-tool-kit
Version: 1.0.1
Summary: 
Author: ahnsv
Author-email: ahnsv@bc.edu
Requires-Python: >=3.9,<4.0
Classifier: Programming Language :: Python :: 3
Classifier: Programming Language :: Python :: 3.9
Classifier: Programming Language :: Python :: 3.10
Classifier: Programming Language :: Python :: 3.11
Classifier: Programming Language :: Python :: 3.12
Requires-Dist: google-cloud-bigquery (>=3.13.0,<4.0.0)
Requires-Dist: sqlparse (>=0.4.4,<0.5.0)
Requires-Dist: typer[all] (>=0.9.0,<0.10.0)
